shapG/__init__.py
shapG/plot.py
shapG/shapley.py
shapG/utils.py
shapg-0.13.4.dist-info/licenses/LICENSE
shapg-0.13.4.dist-info/METADATA
shapg-0.13.4.dist-info/WHEEL
shapg-0.13.4.dist-info/top_level.txt
shapg-0.13.4.dist-info/RECORD
